vector/__init__.py
vector/activation.py
vector/random.py
vector_ai_ml-0.0.3.dist-info/LICENSE
vector_ai_ml-0.0.3.dist-info/METADATA
vector_ai_ml-0.0.3.dist-info/WHEEL
vector_ai_ml-0.0.3.dist-info/top_level.txt
vector_ai_ml-0.0.3.dist-info/RECORD
