Metadata-Version: 2.1
Name: vector-ai-ml
Version: 0.0.3
Summary: A simple python vector package.
Author: AtlasAerospace (Alexander Armitage)
Keywords: python,math,ai,ml,artificialintelligence
Classifier: Development Status :: 1 - Planning
Classifier: Intended Audience :: Developers
Classifier: Programming Language :: Python :: 3
Classifier: Operating System :: Unix
Classifier: Operating System :: MacOS :: MacOS X
Classifier: Operating System :: Microsoft :: Windows
License-File: LICENSE
